whost/__init__.py
whost/common.py
whost/devices.py
whost/network.py
whost/ui/__init__.py
whost/ui/cli.py
whost/ui/credentials.py
whost/ui/devices.py
whost/ui/home.py
whost/ui/network.py
whost-config
whost-configurator
whost-restart-all
whost-setup
whost-start-all
whost-start-worker
whost-stop-all
whost-update
whost-0.2.dist-info/entry_points.txt
whost-0.2.dist-info/WHEEL
whost-0.2.dist-info/METADATA
whost-0.2.dist-info/RECORD
