Metadata-Version: 2.1
Name: whost
Version: 0.2
Summary: Cardshop Writer Host Tools
Home-page: https://www.kiwix.org/kiwix-hotspot/
Author: renaud gaudin
Author-email: reg@kiwix.org
Requires-Python: >=3.6,<4.0
Classifier: Programming Language :: Python :: 3
Classifier: Programming Language :: Python :: 3.6
Classifier: Programming Language :: Python :: 3.7
Classifier: Programming Language :: Python :: 3.8
Classifier: Programming Language :: Python :: 3.9
Requires-Dist: PyYaml (>=3.13,<4.0)
Requires-Dist: colorama (>=0.4.1,<0.5.0)
Requires-Dist: humanfriendly (>=4.17,<5.0)
Requires-Dist: ipython (>=7.2,<8.0)
Requires-Dist: netifaces (>=0.10.7,<0.11.0)
Requires-Dist: requests (>=2.21,<3.0)
Requires-Dist: tabulate (>=0.8.2,<0.9.0)
Requires-Dist: unidecode (>=1.0,<2.0)
Project-URL: Repository, https://github.com/kiwix/cardshop
